ai_reviewer/__init__.py
ai_reviewer/cli.py
ai_reviewer/reviewer.py
ai_reviewer/agents/__init__.py
ai_reviewer/core/__init__.py
ai_reviewer/core/config.py
ai_reviewer/core/formatter.py
ai_reviewer/core/models.py
ai_reviewer/integrations/__init__.py
ai_reviewer/integrations/base.py
ai_reviewer/integrations/gemini.py
ai_reviewer/integrations/github.py
ai_reviewer/integrations/gitlab.py
ai_reviewer/integrations/prompts.py
ai_reviewer/llm/__init__.py
ai_reviewer/utils/__init__.py
ai_reviewer/utils/gemini.py
ai_reviewer/utils/language.py
ai_reviewer/utils/retry.py
ai_reviewer/utils/time.py
ai_reviewbot-1.0.0a3.dist-info/METADATA
ai_reviewbot-1.0.0a3.dist-info/WHEEL
ai_reviewbot-1.0.0a3.dist-info/entry_points.txt
ai_reviewbot-1.0.0a3.dist-info/licenses/LICENSE
ai_reviewbot-1.0.0a3.dist-info/licenses/NOTICE
ai_reviewbot-1.0.0a3.dist-info/RECORD
