Metadata-Version: 2.4
Name: ai-reviewbot
Version: 1.0.0a3
Summary: AI-powered code review agent for CI/CD pipelines
Project-URL: Homepage, https://github.com/KonstZiv/ai-code-reviewer
Project-URL: Documentation, https://konstziv.github.io/ai-code-reviewer
Project-URL: Repository, https://github.com/KonstZiv/ai-code-reviewer
Project-URL: Issues, https://github.com/KonstZiv/ai-code-reviewer/issues
Author-email: Kostyantin Zivenko <kos.zivenko@gmail.com>
License: Apache-2.0
License-File: LICENSE
License-File: NOTICE
Keywords: ai,ci-cd,code-review,github,gitlab,llm
Classifier: Development Status :: 3 - Alpha
Classifier: Intended Audience :: Developers
Classifier: License :: OSI Approved :: Apache Software License
Classifier: Programming Language :: Python :: 3.13
Classifier: Programming Language :: Python :: 3.14
Requires-Python: >=3.13
Requires-Dist: aiofiles>=25.1.0
Requires-Dist: anthropic>=0.76.0
Requires-Dist: click>=8.3.1
Requires-Dist: gitpython>=3.1.46
Requires-Dist: google-api-core>=2.29.0
Requires-Dist: google-genai>=1.59.0
Requires-Dist: httpx>=0.28.1
Requires-Dist: langchain-anthropic>=1.3.1
Requires-Dist: langchain-deepseek>=1.0.1
Requires-Dist: langchain-google-genai>=4.2.0
Requires-Dist: langchain-ollama>=1.0.1
Requires-Dist: langchain-openai>=1.1.7
Requires-Dist: langchain>=1.2.6
Requires-Dist: langgraph>=1.0.6
Requires-Dist: openai>=2.15.0
Requires-Dist: pydantic-settings>=2.12.0
Requires-Dist: pydantic>=2.12.5
Requires-Dist: pygithub>=2.8.1
Requires-Dist: python-dotenv>=1.2.1
Requires-Dist: python-gitlab>=7.1.0
Requires-Dist: python-iso639>=0.0.10
Requires-Dist: pyyaml>=6.0.3
Requires-Dist: rich>=14.2.0
Requires-Dist: tenacity>=9.0.0
Requires-Dist: typer>=0.21.1
